oarepo_model_builder_requests/__init__.py
oarepo_model_builder_requests/datatypes/__init__.py
oarepo_model_builder_requests/datatypes/components/__init__.py
oarepo_model_builder_requests/datatypes/components/requests_model/__init__.py
oarepo_model_builder_requests/datatypes/components/requests_model/record_item.py
oarepo_model_builder_requests/datatypes/components/requests_model/requests.py
oarepo_model_builder_requests/datatypes/components/requests_model/resolver.py
oarepo_model_builder_requests/datatypes/components/requests_model/service.py
oarepo_model_builder_requests/datatypes/components/requests_model/tests.py
oarepo_model_builder_requests/datatypes/components/requests_model/ui_marshmallow.py
oarepo_model_builder_requests/datatypes/components/requests_model/ui_resolver.py
oarepo_model_builder_requests/invenio/__init__.py
oarepo_model_builder_requests/invenio/invenio_requests_builder_base.py
oarepo_model_builder_requests/invenio/invenio_requests_config.py
oarepo_model_builder_requests/invenio/invenio_requests_resolvers.py
oarepo_model_builder_requests/invenio/invenio_requests_views.py
oarepo_model_builder_requests/invenio/invenio_requests_views_app.py
oarepo_model_builder_requests/invenio/overriding_builder.py
oarepo_model_builder_requests/invenio/record_request_types_api_views.py
oarepo_model_builder_requests/invenio/record_request_types_app_views.py
oarepo_model_builder_requests/invenio/record_request_types_config.py
oarepo_model_builder_requests/invenio/record_request_types_ext_resource.py
oarepo_model_builder_requests/invenio/record_request_types_resource_setup_cfg.py
oarepo_model_builder_requests/invenio/record_requests_api_views.py
oarepo_model_builder_requests/invenio/record_requests_app_views.py
oarepo_model_builder_requests/invenio/record_requests_config.py
oarepo_model_builder_requests/invenio/record_requests_ext_resource.py
oarepo_model_builder_requests/invenio/record_requests_resource_setup_cfg.py
oarepo_model_builder_requests-4.1.10.dist-info/licenses/LICENSE
oarepo_model_builder_requests-4.1.10.dist-info/METADATA
oarepo_model_builder_requests-4.1.10.dist-info/WHEEL
oarepo_model_builder_requests-4.1.10.dist-info/entry_points.txt
oarepo_model_builder_requests-4.1.10.dist-info/top_level.txt
oarepo_model_builder_requests-4.1.10.dist-info/RECORD
