Metadata-Version: 2.4
Name: oarepo-model-builder-requests
Version: 4.1.10
License-File: LICENSE
Requires-Dist: oarepo-model-builder
Requires-Dist: oarepo-model-builder-tests
Provides-Extra: tests
Requires-Dist: pytest-invenio>=1.4.11; extra == "tests"
Dynamic: license-file
